hill_climber/__init__.py
hill_climber/climber_functions.py
hill_climber/config.py
hill_climber/dashboard_data.py
hill_climber/dashboard_plots.py
hill_climber/dashboard_ui.py
hill_climber/database.py
hill_climber/optimizer.py
hill_climber/optimizer_state.py
hill_climber/plotting_functions.py
hill_climber/progress_dashboard.py
hill_climber/replica_exchange.py
hill_climber/replica_worker.py
parallel_hill_climber-3.2.0.dist-info/licenses/LICENSE
parallel_hill_climber-3.2.0.dist-info/METADATA
parallel_hill_climber-3.2.0.dist-info/WHEEL
parallel_hill_climber-3.2.0.dist-info/entry_points.txt
parallel_hill_climber-3.2.0.dist-info/top_level.txt
parallel_hill_climber-3.2.0.dist-info/RECORD
