Metadata-Version: 2.4
Name: parallel-hill-climber
Version: 3.2.0
Summary: A Python package for hill climbing optimization with replica exchange and simulated annealing
Author-email: gperdrizet <george@perdrizet.org>
License: GPLv3
Project-URL: Homepage, https://github.com/gperdrizet/hill_climber
Project-URL: Documentation, https://gperdrizet.github.io/hill_climber
Project-URL: Repository, https://github.com/gperdrizet/hill_climber
Project-URL: Issues, https://github.com/gperdrizet/hill_climber/issues
Project-URL: PyPI, https://pypi.org/project/parallel-hill-climber
Keywords: optimization,replica-exchange,parallel-tempering,simulated-annealing,hill-climbing,machine-learning,data-science
Classifier: Development Status :: 4 - Beta
Classifier: Intended Audience :: Science/Research
Classifier: Intended Audience :: Developers
Classifier: Programming Language :: Python :: 3
Classifier: Programming Language :: Python :: 3.10
Classifier: Programming Language :: Python :: 3.11
Classifier: Programming Language :: Python :: 3.12
Classifier: Topic :: Scientific/Engineering
Classifier: Topic :: Scientific/Engineering :: Mathematics
Classifier: Topic :: Software Development :: Libraries :: Python Modules
Requires-Python: >=3.10
License-File: LICENSE
Requires-Dist: numpy>=1.20.0
Requires-Dist: pandas>=1.3.0
Requires-Dist: scipy>=1.7.0
Requires-Dist: matplotlib>=3.4.0
Requires-Dist: numba>=0.54.0
Provides-Extra: dev
Requires-Dist: pytest>=7.0.0; extra == "dev"
Requires-Dist: pytest-cov>=3.0.0; extra == "dev"
Requires-Dist: ipykernel>=6.0.0; extra == "dev"
Requires-Dist: scikit-learn>=1.0.0; extra == "dev"
Provides-Extra: dashboard
Requires-Dist: streamlit>=1.28.0; extra == "dashboard"
Requires-Dist: plotly>=5.14.0; extra == "dashboard"
Dynamic: license-file
